[{"NOME":"Carne seca e Queijo Coalho","CATEGORIA":"Tapioca","SUB_CAT":"SIM ","preco_1":26.0,"preco_2":null,"IGREDIENTES":null,"IMAGEM":"tapioca-carne-seca.png | Tapiocas (2).jpg |  Tapiocas (8).jpg"},{"NOME":"Coco e leite condensado","CATEGORIA":"Tapioca","SUB_CAT":"SIM ","preco_1":22.0,"preco_2":null,"IGREDIENTES":null,"IMAGEM":"Tapiocas (3).jpg"},{"NOME":"Com Manteiga","CATEGORIA":"Tapioca","SUB_CAT":"SIM ","preco_1":13.0,"preco_2":null,"IGREDIENTES":null,"IMAGEM":"Tapiocas (3).jpg"},{"NOME":"Frango com Queijo","CATEGORIA":"Tapioca","SUB_CAT":"SIM ","preco_1":23.0,"preco_2":null,"IGREDIENTES":null,"IMAGEM":"Tapiocas (3).jpg"},{"NOME":"Mussarela","CATEGORIA":"Tapioca","SUB_CAT":"SIM ","preco_1":20.0,"preco_2":null,"IGREDIENTES":null,"IMAGEM":"Tapiocas (3).jpg"},{"NOME":"Peito de Peru com Minas","CATEGORIA":"Tapioca","SUB_CAT":"SIM ","preco_1":26.0,"preco_2":null,"IGREDIENTES":null,"IMAGEM":"Tapiocas (3).jpg"},{"NOME":"Queijo coalho","CATEGORIA":"Tapioca","SUB_CAT":"SIM ","preco_1":24.0,"preco_2":null,"IGREDIENTES":null,"IMAGEM":"Tapiocas (3).jpg"},{"NOME":"Queijo com presunto","CATEGORIA":"Tapioca","SUB_CAT":"SIM ","preco_1":20.0,"preco_2":null,"IGREDIENTES":null,"IMAGEM":"Tapiocas (3).jpg"},{"NOME":"Queijo Minas","CATEGORIA":"Tapioca","SUB_CAT":"SIM ","preco_1":20.0,"preco_2":null,"IGREDIENTES":null,"IMAGEM":"Tapiocas (7).jpg"},{"NOME":"Simples","CATEGORIA":"Tapioca","SUB_CAT":"SIM ","preco_1":12.0,"preco_2":null,"IGREDIENTES":null,"IMAGEM":"Tapiocas (1).jpg | Tapiocas (3).jpg"}]